{"-1001070571493":{"moderators":{"143099335":"Naz24","149387873":"None","203561736":"MardeMajazi","351917235":"None","367613346":"sharrim56","378485529":"zeus_boto","394156814":"None","439851598":"None","451053814":"Hokoomat_ashrarrrr","462905647":"Sharrrrim57","468934697":"None","469435762":"None","475258943":"Shsh7677","491270145":"None"},"set_owner":"299746177","settings":{"flood_num":"5","lock_abuse":"yes","lock_all":"no","lock_arabic":"no","lock_audio":"no","lock_bot":"yes","lock_bye":"yes","lock_cmd":"no","lock_contact":"yes","lock_document":"yes","lock_edit":"no","lock_english":"no","lock_flood":"no","lock_forward":"yes","lock_gif":"no","lock_link":"yes","lock_photo":"no","lock_spam":"no","lock_sticker":"no","lock_strict":"no","lock_tag":"yes","lock_text":"no","lock_tgservice":"yes","lock_username":"no","lock_video":"no","lock_voice":"no","lock_wlc":"no","show_edit":"no"}},"-1001116083302":{"moderators":{"203561736":"MardeMajazi","297729880":"poshtibani_matador","326551357":"Professor_telegram","413924974":"ROBOGUARDTM","451618866":"None","452979721":"guard3","458448440":"AntispmGUARD3"},"set_owner":"386420399","settings":{"flood_num":"5","lock_abuse":"no","lock_all":"no","lock_arabic":"no","lock_audio":"no","lock_bot":"no","lock_bye":"no","lock_cmd":"no","lock_contact":"no","lock_document":"no","lock_edit":"no","lock_english":"no","lock_flood":"yes","lock_forward":"yes","lock_gif":"no","lock_link":"yes","lock_photo":"no","lock_spam":"yes","lock_sticker":"no","lock_strict":"no","lock_tag":"no","lock_text":"no","lock_tgservice":"yes","lock_username":"no","lock_video":"no","lock_voice":"no","lock_wlc":"no","show_edit":"no"}},"-1001120969820":{"moderators":{"394437347":"Miladhjv112","421155846":"Miladhjv111"},"set_owner":"0","settings":{"flood_num":"5","lock_abuse":"no","lock_all":"no","lock_arabic":"no","lock_audio":"no","lock_bot":"no","lock_bye":"no","lock_cmd":"no","lock_contact":"no","lock_document":"no","lock_edit":"no","lock_english":"no","lock_flood":"yes","lock_forward":"yes","lock_gif":"no","lock_link":"yes","lock_photo":"no","lock_spam":"yes","lock_sticker":"no","lock_strict":"no","lock_tag":"no","lock_text":"no","lock_tgservice":"yes","lock_username":"no","lock_video":"no","lock_voice":"no","lock_wlc":"no","show_edit":"no"}},"-1001125866953":{"moderators":{"284081539":"Nbnmbfjvvjgfj","301046421":"None","315236525":"Ghcjvhcjvjvjv","338952421":"Mojtaba112223","341263404":"Mojtaba65743","365084663":"None","371417642":"ASALTKPR","394437347":"Miladhjv112","404724600":"Bfjgghdyxycyxxug","409077844":"Mojtaba66680","410231153":"Ejoodi","421155846":"Miladhjv111","453696277":"Mojtaba000111","480151594":"Gentelman45","491152030":"Gentelman337","499088567":"Mojtaba09080","68774969":"Geshtapooooo"},"set_owner":"344656403","settings":{"flood_num":"5","lock_abuse":"no","lock_all":"no","lock_arabic":"no","lock_audio":"no","lock_bot":"no","lock_bye":"no","lock_cmd":"yes","lock_contact":"no","lock_document":"no","lock_edit":"no","lock_english":"no","lock_flood":"no","lock_forward":"yes","lock_gif":"no","lock_link":"yes","lock_photo":"no","lock_spam":"yes","lock_sticker":"no","lock_strict":"no","lock_tag":"no","lock_text":"no","lock_tgservice":"yes","lock_username":"no","lock_video":"no","lock_voice":"no","lock_wlc":"no","show_edit":"no"}},"-1001127890477":{"moderators":[],"set_owner":"0","settings":{"flood_num":"5","lock_abuse":"no","lock_all":"no","lock_arabic":"no","lock_audio":"no","lock_bot":"no","lock_bye":"no","lock_cmd":"no","lock_contact":"no","lock_document":"no","lock_edit":"no","lock_english":"no","lock_flood":"yes","lock_forward":"yes","lock_gif":"no","lock_link":"no","lock_photo":"no","lock_spam":"yes","lock_sticker":"no","lock_strict":"no","lock_tag":"no","lock_text":"no","lock_tgservice":"yes","lock_username":"no","lock_video":"no","lock_voice":"no","lock_wlc":"no","show_edit":"no"}},"-1001128478447":{"moderators":{"136292984":"tarane6346","326551357":"Professor_telegram","465884373":"None"},"set_owner":"203561736","settings":{"flood_num":"5","lock_abuse":"no","lock_all":"no","lock_arabic":"no","lock_audio":"no","lock_bot":"yes","lock_bye":"yes","lock_cmd":"no","lock_contact":"no","lock_document":"no","lock_edit":"no","lock_english":"no","lock_flood":"no","lock_forward":"yes","lock_gif":"no","lock_link":"yes","lock_photo":"yes","lock_spam":"yes","lock_sticker":"no","lock_strict":"no","lock_tag":"no","lock_text":"no","lock_tgservice":"yes","lock_username":"no","lock_video":"yes","lock_voice":"yes","lock_wlc":"yes","set_link":"https://t.me/joinchat/DCIbCENDNu_vKbNjyN7Ovg","show_edit":"no"}},"-1001133172163":{"moderators":{"396699548":"Malake_telegramm_b30k","415803644":"na_ghalb_darm_na_ehsas_bsik_baw"},"set_owner":"415803644","settings":{"flood_num":"5","lock_abuse":"no","lock_all":"no","lock_arabic":"no","lock_audio":"no","lock_bot":"no","lock_bye":"no","lock_cmd":"no","lock_contact":"no","lock_document":"no","lock_edit":"no","lock_english":"no","lock_flood":"yes","lock_forward":"yes","lock_gif":"no","lock_link":"yes","lock_photo":"no","lock_spam":"yes","lock_sticker":"no","lock_strict":"no","lock_tag":"no","lock_text":"no","lock_tgservice":"yes","lock_username":"no","lock_video":"no","lock_voice":"no","lock_wlc":"no","show_edit":"no"}},"-1001148077521":{"moderators":{"394437347":"Miladhjv112","421155846":"Miladhjv111","441578226":"None"},"set_owner":"415803644","settings":{"flood_num":"8","lock_abuse":"no","lock_all":"no","lock_arabic":"no","lock_audio":"no","lock_bot":"yes","lock_bye":"no","lock_cmd":"no","lock_contact":"no","lock_document":"no","lock_edit":"no","lock_english":"no","lock_flood":"no","lock_forward":"yes","lock_gif":"no","lock_link":"yes","lock_photo":"no","lock_spam":"no","lock_sticker":"no","lock_strict":"no","lock_tag":"no","lock_text":"no","lock_tgservice":"yes","lock_username":"no","lock_video":"no","lock_voice":"no","lock_wlc":"no","set_link":"https://t.me/joinchat/GEEHmURuRdEplvV3nCrjFQ","show_edit":"no"}},"-1001173327630":{"moderators":{"386420399":"None"},"set_owner":"203561736","settings":{"flood_num":"5","lock_abuse":"no","lock_all":"no","lock_arabic":"no","lock_audio":"no","lock_bot":"no","lock_bye":"no","lock_cmd":"no","lock_contact":"no","lock_document":"no","lock_edit":"no","lock_english":"no","lock_flood":"yes","lock_forward":"yes","lock_gif":"yes","lock_link":"yes","lock_photo":"no","lock_spam":"yes","lock_sticker":"no","lock_strict":"no","lock_tag":"no","lock_text":"no","lock_tgservice":"yes","lock_username":"no","lock_video":"no","lock_voice":"no","lock_wlc":"no","show_edit":"no"}},"-1001211846427":{"moderators":[],"set_owner":"0","settings":{"flood_num":"5","lock_abuse":"no","lock_all":"no","lock_arabic":"no","lock_audio":"no","lock_bot":"no","lock_bye":"no","lock_cmd":"no","lock_contact":"no","lock_document":"no","lock_edit":"no","lock_english":"no","lock_flood":"yes","lock_forward":"yes","lock_gif":"no","lock_link":"yes","lock_photo":"no","lock_spam":"yes","lock_sticker":"no","lock_strict":"no","lock_tag":"no","lock_text":"no","lock_tgservice":"yes","lock_username":"no","lock_video":"no","lock_voice":"no","lock_wlc":"no","show_edit":"no"}},"groups":{"-1001070571493":-1001070571493,"-1001116083302":-1001116083302,"-1001120969820":-1001120969820,"-1001125866953":-1001125866953,"-1001127890477":-1001127890477,"-1001128478447":-1001128478447,"-1001133172163":-1001133172163,"-1001148077521":-1001148077521,"-1001173327630":-1001173327630,"-1001211846427":-1001211846427}}